yara_dsl/__init__.py
yara_dsl/rule.py
yara_dsl/semantic.py
yara_dsl/string.py
yara_dsl/validator.py
yara_dsl-0.0.0.dist-info/licenses/LICENSE
yara_dsl-0.0.0.dist-info/METADATA
yara_dsl-0.0.0.dist-info/WHEEL
yara_dsl-0.0.0.dist-info/RECORD
