Metadata-Version: 2.4
Name: yara-dsl
Version: 0.0.0
Summary: Semantic YARA DSL - Construction-time validation
License: MIT
License-File: LICENSE
Author: Sanjeevikumar S
Author-email: sanjeevikumar15@gmail.com
Requires-Python: >=3.10,<4.0
Classifier: License :: OSI Approved :: MIT License
Classifier: Programming Language :: Python :: 3
Classifier: Programming Language :: Python :: 3.10
Classifier: Programming Language :: Python :: 3.11
Classifier: Programming Language :: Python :: 3.12
Classifier: Programming Language :: Python :: 3.13
Classifier: Programming Language :: Python :: 3.14
